MyTopsis/__init__.py
MyTopsis/topsis.py
Topsis_UCS633/__init__.py
Topsis_UCS633/topsis.py
Topsis_UCS633-1.0.1.dist-info/DESCRIPTION.rst
Topsis_UCS633-1.0.1.dist-info/METADATA
Topsis_UCS633-1.0.1.dist-info/RECORD
Topsis_UCS633-1.0.1.dist-info/WHEEL
Topsis_UCS633-1.0.1.dist-info/entry_points.txt
Topsis_UCS633-1.0.1.dist-info/metadata.json
Topsis_UCS633-1.0.1.dist-info/top_level.txt
