Metadata-Version: 2.0
Name: Topsis-UCS633
Version: 1.0.1
Summary: A topsis Package Project of UCS633
Home-page: UNKNOWN
Author: Divya Arora
Author-email: divyaarora2k@gmail.com
License: MIT
Platform: UNKNOWN
Classifier: Programming Language :: Python
Classifier: Operating System :: OS Independent
Classifier: License :: OSI Approved :: Python Software Foundation License
